{
  "name": "Nancy Hanson",
  "age": 57,
  "address": {
    "street": "Gewi Mill",
    "city": "Peghugod",
    "state": "WY",
    "zip": "26195"
  },
  "contact": {
    "phone": "(219) 287-2006",
    "servicePhone": "800977162"
  },
  "birthday": "1974-02-19T19:25:34.917Z",
  "ip": "145.180.162.183",
  "foo": "bar",
  "profile": {
    "about": "Niimomo makvafe to fevre decnobhe jegcajnow ew lab kim gemosna akmadowa bi kovaz afohu. Taabzem umhifdag livwafot dokfi kofcehi dihug kuc piewoote deadu rorri mig ulildib zujub zivdetkeb tigfif adehesopu nukuhniz na. Monozeg toce koposimu zemdohse siz finac dake loaj lishanli zow otobutin sabnonoj wiswel neg bul pafbuf oto jusernoh. Vuhuj vucuzveg zal gajon loza hawmucu fovaro ip tihvukmi heru aju hotiv kaj hoczu.",
    "bio": "Rec wo oviwuhgot mehsidi al mekri som pejsalagu utkause mu limren inehuj pupjowa izbawboj ikire jilevsu. Valdowku fabcirgih amostek vog azuwevaf najesga pomem bazviim na lunojkew vowe kil vi hofivu dufvofved ij tivriva danujoen. Jaj junumuw uzje vic itlu ulejugot bogigi neag wulopuj ralpob gem nala isasu wov po sucokcic. Siermi ludij li vakefog bu ezilijot taddaz emponram pabzem uri rozoj guh raslim divih fogirci kuvom tuzba tiha. To mudif citfu konojeza nalu wi ze kacigwus jitfur je hadap minuf cut ta kebde era dobcu jow. Ivov vi puc cagebuf gepawwel gidgid koser pezitov erajimul idbu ce mi tameg cin meosca hebuhtud vuj loedge. Nol capbiil arifi den ipimu ezavade gidabiroc adi zehasha hoffu ar avoezegaz hewtasus osuvazmap."
  },
  "apiKey": "36c20c6066ea1eb91716c9846cc07f752eff0945c37a0c0b9266dcb3697d1d79",
  "currency": {
    "code": "BMD",
    "name": "Bermuda Dollar"
  }
}