{
  "name": "Christian Reese",
  "age": 49,
  "address": {
    "street": "Uwow Drive",
    "city": "Pictetkoh",
    "state": "NH",
    "zip": "14242"
  },
  "contact": {
    "phone": "(684) 732-8078",
    "servicePhone": "800784694"
  },
  "birthday": "1967-06-19T16:09:13.866Z",
  "ip": "35.85.191.225",
  "foo": "bar",
  "profile": {
    "about": "Ik apu jarjiraru ilved sutves ho loc sosgi vuwigji rugab degtawza fi. Vuhel ep fimpapmom icaf wup ohefso abfab sajaku lus go fe movele ofeod tazzicwo juzehufu. Kenbi pa havba ce guj zul kojivo mubeze lersaha lazozaf gogel debisli tocomgap. Iv kuigzu cupu cenacsuf ji nal fijtatgu tohtamaz nuvzoke nalzipa voplocawo hik jokwe kujuzha ew kudno ban va. Jo gek munalvow kod vomulo tijbigoj am nuto ig so teafu nujaz. Usonisuc momhow bo goldees ufeekzu ow roanimo huswi vemurodaw bupnokna wa cokmapeha vegac upekohjo visrodci wismevep.",
    "bio": "En tomef igdoviz veob mokoler ehmupod zifo voc vovino jenuneb tol ar se gofcuw be wiwape. Diwgubaf keci sadmub tahhiw wo mot ro foh gu debiw noz lol cunmi vu eg ricoz edka. Ur gan torlah dop hiigewev jez edoaj obveke pu eksamo resah ro mila. Ib moewe atotalu bos riba wak unde ciowagu haasa ondico deh lotve fojgak agavacu edhe sereeno sag uzi."
  },
  "apiKey": "8a40d256cb3d49b502276fa30a7d38e9f052f724d93b15dcf4957091fa598ecc",
  "currency": {
    "code": "TTD",
    "name": "Trinidad and Tobago Dollar"
  }
}